main.py
makeitseg2-1.0.0.dist-info/LICENSE
makeitseg2-1.0.0.dist-info/METADATA
makeitseg2-1.0.0.dist-info/WHEEL
makeitseg2-1.0.0.dist-info/top_level.txt
makeitseg2-1.0.0.dist-info/RECORD
