Metadata-Version: 2.1
Name: makeitseg2
Version: 1.0.0
Summary: makeitseg2
Author: Shanu Biswas
Author-email: shanubiswas119@gmail.com
Keywords: segy,su,seismic,seg2,segy to seg2 converter,su to seg2 converter,segy to dat file converter,su to dat file converter,segy to dat file converter using python
Classifier: Development Status :: 4 - Beta
Classifier: Intended Audience :: Education
Classifier: Intended Audience :: Science/Research
Classifier: Programming Language :: Python :: 3
Classifier: Operating System :: OS Independent
License-File: LICENSE
Requires-Dist: obspy
